setup.py
plaza_bridge/__init__.py
plaza_bridge/blocks.py
plaza_bridge/bridge.py
plaza_bridge/extra_data.py
plaza_bridge/protocol.py
plaza_bridge/registration.py
plaza_bridge/service_configuration.py
plaza_bridge/utils.py
plaza_bridge.egg-info/PKG-INFO
plaza_bridge.egg-info/SOURCES.txt
plaza_bridge.egg-info/dependency_links.txt
plaza_bridge.egg-info/not-zip-safe
plaza_bridge.egg-info/requires.txt
plaza_bridge.egg-info/top_level.txt